morpyengine/Constants.py
morpyengine/Engine.py
morpyengine/__init__.py
morpyengine/Systems/Mouse.py
morpyengine/Systems/Render.py
morpyengine/Systems/__init__.py
morpyengine-0.0.2.dist-info/LICENSE
morpyengine-0.0.2.dist-info/METADATA
morpyengine-0.0.2.dist-info/WHEEL
morpyengine-0.0.2.dist-info/top_level.txt
morpyengine-0.0.2.dist-info/RECORD
